{
  "menu": [
    {
      "id": 1,
      "title": "Bryggkaffe",
      "desc": "Bryggd på månadens bönor.",
      "price": 39
    },
    {
      "id": 2,
      "title": "Caffè Doppio",
      "desc": "Bryggd på månadens bönor.",
      "price": 49
    },
    {
      "id": 3,
      "title": "Cappuccino",
      "desc": "Bryggd på månadens bönor.",
      "price": 49
    },
    {
      "id": 4,
      "title": "Latte Macchiato",
      "desc": "Bryggd på månadens bönor.",
      "price": 49
    },
    {
      "id": 5,
      "title": "Kaffe Latte",
      "desc": "Bryggd på månadens bönor.",
      "price": 54
    },
    {
      "id": 6,
      "title": "Cortado",
      "desc": "Bryggd på månadens bönor.",
      "price": 39
    }
  ],
  "orders": [
    {
      "id": [
        2,
        5
      ],
      "title": [
        "Caffè Doppio",
        "Kaffe Latte"
      ],
      "price": 103,
      "ETA": "May 3, 2021 5:22 PM",
      "orderNumber": "meKED",
      "userId": "Pquk",
      "status": "Delivered"
    },
    {
      "id": [
        1
      ],
      "title": [
        "Bryggkaffe"
      ],
      "price": 39,
      "ETA": "May 3, 2021 5:16 PM",
      "orderNumber": "ve_l5",
      "userId": "Pquk",
      "status": "Delivered"
    },
    {
      "id": [
        1,
        3,
        5
      ],
      "title": [
        "Bryggkaffe",
        "Cappuccino",
        "Kaffe Latte"
      ],
      "price": 142,
      "ETA": "May 3, 2021 5:22 PM",
      "orderNumber": "P0vko",
      "userId": "dBr7",
      "status": "Delivered"
    },
    {
      "id": [
        6
      ],
      "title": [
        "Cortado"
      ],
      "price": 39,
      "ETA": "May 3, 2021 5:17 PM",
      "orderNumber": "JWoRC",
      "userId": "dBr7",
      "status": "Delivered"
    },
    {
      "id": [
        3
      ],
      "title": [
        "Cappuccino"
      ],
      "price": 49,
      "ETA": "May 3, 2021 5:20 PM",
      "orderNumber": "4RZ7r",
      "userId": "Pquk",
      "status": "Delivered"
    },
    {
      "id": [
        4,
        5
      ],
      "title": [
        "Latte Macchiato",
        "Kaffe Latte"
      ],
      "price": 103,
      "ETA": "May 3, 2021 5:37 PM",
      "orderNumber": "hKxtV",
      "userId": "dBr7"
    },
    {
      "id": [
        6
      ],
      "title": [
        "Cortado"
      ],
      "price": 39,
      "ETA": "May 3, 2021 5:46 PM",
      "orderNumber": "BZXe3",
      "userId": "Pquk"
    }
  ],
  "users": [
    {
      "id": "Pquk",
      "username": "Ann",
      "password": 123
    },
    {
      "id": "dBr7",
      "username": "William",
      "password": 123
    }
  ]
}